rem_math-0.1.5.dist-info/METADATA
rem_math-0.1.5.dist-info/WHEEL
rem_math-0.1.5.dist-info/licenses/LICENSE
rem_math/__init__.py
rem_math/rem_math.cp311-win_amd64.pyd
rem_math-0.1.5.dist-info/RECORD
