Metadata-Version: 2.4
Name: rem_math
Version: 0.1.5
License-File: LICENSE
Summary: 
Author-email: WrldEngine <kamran_pulatov@outlook.com>
Requires-Python: >=3.11
